gurufocus_mcp/__init__.py
gurufocus_mcp/__main__.py
gurufocus_mcp/config.py
gurufocus_mcp/context.py
gurufocus_mcp/errors.py
gurufocus_mcp/formatting.py
gurufocus_mcp/py.typed
gurufocus_mcp/query.py
gurufocus_mcp/server.py
gurufocus_mcp/analysis/__init__.py
gurufocus_mcp/analysis/qgarp.py
gurufocus_mcp/analysis/risk.py
gurufocus_mcp/models/__init__.py
gurufocus_mcp/models/qgarp.py
gurufocus_mcp/models/risk.py
gurufocus_mcp/resources/__init__.py
gurufocus_mcp/resources/schemas.py
gurufocus_mcp/resources/stocks.py
gurufocus_mcp/tools/__init__.py
gurufocus_mcp/tools/analysis.py
gurufocus_mcp/tools/economic.py
gurufocus_mcp/tools/etfs.py
gurufocus_mcp/tools/gurus.py
gurufocus_mcp/tools/insiders.py
gurufocus_mcp/tools/personal.py
gurufocus_mcp/tools/politicians.py
gurufocus_mcp/tools/reference.py
gurufocus_mcp/tools/schemas.py
gurufocus_mcp/tools/stocks.py
gurufocus_mcp-0.6.0.dist-info/METADATA
gurufocus_mcp-0.6.0.dist-info/WHEEL
gurufocus_mcp-0.6.0.dist-info/entry_points.txt
gurufocus_mcp-0.6.0.dist-info/RECORD
