Metadata-Version: 2.4
Name: gurufocus-mcp
Version: 0.6.0
Summary: Unofficial MCP server for GuruFocus financial data
Project-URL: Homepage, https://github.com/u-daveblack/gurufocus-mcp
Project-URL: Documentation, https://github.com/u-daveblack/gurufocus-mcp#readme
Project-URL: Repository, https://github.com/u-daveblack/gurufocus-mcp
Author: David Black
License-Expression: MIT
Keywords: ai,finance,gurufocus,llm,mcp,model-context-protocol
Classifier: Development Status :: 3 - Alpha
Classifier: Intended Audience :: Developers
Classifier: Intended Audience :: Financial and Insurance Industry
Classifier: License :: OSI Approved :: MIT License
Classifier: Programming Language :: Python :: 3
Classifier: Programming Language :: Python :: 3.11
Classifier: Programming Language :: Python :: 3.12
Classifier: Topic :: Office/Business :: Financial :: Investment
Classifier: Typing :: Typed
Requires-Python: >=3.11
Requires-Dist: fastmcp>=0.4
Requires-Dist: gurufocus-api
Requires-Dist: jmespath>=1.0
Requires-Dist: python-toon>=0.1
Requires-Dist: structlog>=24.0
Provides-Extra: dev
Requires-Dist: mypy>=1.13; extra == 'dev'
Requires-Dist: pytest-asyncio>=0.24; extra == 'dev'
Requires-Dist: pytest-cov>=5.0; extra == 'dev'
Requires-Dist: pytest>=8.0; extra == 'dev'
Requires-Dist: ruff>=0.8; extra == 'dev'
